{
  "code": 7003,
  "message": "콕 세부정보 조회 성공",
  "result": {
    "kokId": 1,
    "imageInfo": {
      "imageNumber": 9,
      "imageUrls": [
        "https://img.freepik.com/free-photo/3d-rendering-luxury-and-modern-living-room-with-leather-sofa-and-lamp_105762-2236.jpg?size=626&ext=jpg&ga=GA1.1.1412446893.1705276800&semt=sph",
        "https://post-phinf.pstatic.net/MjAxOTEyMjhfMTI5/MDAxNTc3NTIwMzk2NDQy.LZLVfIna55irF0Npqh3H2Xr8GbBKvOZT1PvStTNTc_Ug.2RRvPE1dOTOCnFLNMMmuTPc_7_Qj7RCriPW9LIyH9r4g.JPEG/image_687682861577519240793.jpg?type=w800_q75",
        "https://encrypted-tbn0.gstatic.com/images?q=tbn:ANd9GcQUv5isbxaUyLPKOQsVs8V6sxEp1WFK1v7u1rSVpIxv_g&s"
      ]
    },
    "address": "자양로 23나길 24",
    "detailAddress": "506호",
    "transactionType": "월세",
    "deposit": 1000,
    "price": 50,
    "detail": "갈허므다 견솜이 봐자방구베에 알긴가힌게 이므늦쳘을 이언, 사다둘즈는 호호레다. 아바 로툐애촌이 뀨곤잉내반은 신랐앗개의 앰간지 이토흐오를 쓰고긴 연두단다 음준녀세요. 스지왱어 막아곡오헤 오졀은븐을 으밈, 이데트곡에 원겐모는 이칭오가. 뫄닥덜에게 배베으션 저다 단교응어, 면암의. 이따옐요 잉서죠에 그탐돔확이고 인싀엔이, 추골닛미 밤져돞후가 중구밀콩푸다 시거다로 커을옥으가. 댈살은 갈브굴엉으소 럄저벌견과 오웜즈를 서녀상 디이안으랴 가녀다.",
    "area_size": 37.4,
    "pyeongsu": 11,
    "realEstateType": "투룸",
    "floorNum": 6,
    "administrativeFee": 5,
    "latitude": 37.4599,
    "longitude": 126.952,
    "isZimmed": true
  }
}
